MANIFEST.in
README.md
setup.py
Stoffel.egg-info/PKG-INFO
Stoffel.egg-info/SOURCES.txt
Stoffel.egg-info/dependency_links.txt
Stoffel.egg-info/entry_points.txt
Stoffel.egg-info/requires.txt
Stoffel.egg-info/top_level.txt
stoffel/__init__.py
stoffel/__main__.py
stoffel/app.py
stoffel/settings.py
stoffel/core/connect.py
stoffel/core/ggl.py
stoffel/core/msft.py
stoffel/core/utils/paths.py
stoffel/core/utils/project.py
stoffel/core/utils/vba.py
stoffel/core/utils/__pycache__/paths.cpython-38.pyc
stoffel/core/utils/__pycache__/project.cpython-38.pyc
stoffel/core/utils/__pycache__/vba.cpython-38.pyc
stoffel/creds/credentials.json
stoffel/files/empty.txt
stoffel/static/connections.js
stoffel/static/google.js
stoffel/static/jqueryFileTree.css
stoffel/static/jqueryFileTree.js
stoffel/static/semantic.min.css
stoffel/static/semantic.min.js
stoffel/static/components/accordion.css
stoffel/static/components/accordion.js
stoffel/static/components/accordion.min.css
stoffel/static/components/accordion.min.js
stoffel/static/components/ad.css
stoffel/static/components/ad.min.css
stoffel/static/components/api.js
stoffel/static/components/api.min.js
stoffel/static/components/breadcrumb.css
stoffel/static/components/breadcrumb.min.css
stoffel/static/components/button.css
stoffel/static/components/button.min.css
stoffel/static/components/card.css
stoffel/static/components/card.min.css
stoffel/static/components/checkbox.css
stoffel/static/components/checkbox.js
stoffel/static/components/checkbox.min.css
stoffel/static/components/checkbox.min.js
stoffel/static/components/colorize.js
stoffel/static/components/colorize.min.js
stoffel/static/components/comment.css
stoffel/static/components/comment.min.css
stoffel/static/components/container.css
stoffel/static/components/container.min.css
stoffel/static/components/dimmer.css
stoffel/static/components/dimmer.js
stoffel/static/components/dimmer.min.css
stoffel/static/components/dimmer.min.js
stoffel/static/components/divider.css
stoffel/static/components/divider.min.css
stoffel/static/components/dropdown.css
stoffel/static/components/dropdown.js
stoffel/static/components/dropdown.min.css
stoffel/static/components/dropdown.min.js
