Metadata-Version: 1.2
Name: Stoffel
Version: 0.1.2
Summary: A tool to connect Excel/Sheets to Powerpoint/Slides.
Home-page: https://github.com/fifth-partners/stoffel
Author: Nathan Duncan
Author-email: nduncan@fifthpartners.com
License: LGPLv3
Download-URL: https://github.com/fifth-partners/stoffel/archive/v0.1.2.zip
Platform: UNKNOWN
Classifier: Intended Audience :: Developers
Requires-Python: !=3.0.*, !=3.1.*, !=3.2.*, !=3.3.*
